rest_framework_roles/__init__.py
rest_framework_roles/apps.py
rest_framework_roles/decorators.py
rest_framework_roles/exceptions.py
rest_framework_roles/granting.py
rest_framework_roles/parsing.py
rest_framework_roles/patching.py
rest_framework_roles/permissions.py
rest_framework_roles/roles.py
rest_framework_roles-1.1.1.dist-info/LICENSE
rest_framework_roles-1.1.1.dist-info/METADATA
rest_framework_roles-1.1.1.dist-info/WHEEL
rest_framework_roles-1.1.1.dist-info/top_level.txt
rest_framework_roles-1.1.1.dist-info/RECORD
