Metadata-Version: 2.1
Name: rest-framework-roles
Version: 1.1.1
Summary: Role-based permissions for Django REST Framework and vanilla Django.
Home-page: https://github.com/Pithikos/rest-framework-roles
Author: Johan Hanssen Seferidis
Author-email: manossef@gmail.com
License: LICENSE
Keywords: permissions,roles,users,django,rest,drf,acl,security,rest framework,access control
Platform: UNKNOWN
Classifier: Framework :: Django
Classifier: Topic :: Security
Requires-Python: >=3
License-File: LICENSE
